dynkin/__init__.py
dynkin/euler.py
dynkin/frame.py
dynkin/rigid_body.py
dynkin-0.2.1.dist-info/LICENSE
dynkin-0.2.1.dist-info/METADATA
dynkin-0.2.1.dist-info/WHEEL
dynkin-0.2.1.dist-info/top_level.txt
dynkin-0.2.1.dist-info/RECORD
