Metadata-Version: 2.1
Name: dynkin
Version: 0.2.1
Summary: A toolkit for 3D dynamics and kinematics
Home-page: https://github.com/freol35241/pydynkin
Author: Fredrik Olsson
Author-email: freol@outlook.com
Maintainer: Fredrik Olsson
Maintainer-email: freol@outlook.com
License: MIT
Platform: UNKNOWN
Classifier: Development Status :: 4 - Beta
Classifier: Programming Language :: Python :: 3.5
Classifier: Programming Language :: Python :: 3.6
Classifier: Programming Language :: Python :: 3.7
Classifier: Programming Language :: Python :: 3.8
Classifier: Operating System :: OS Independent
Classifier: License :: OSI Approved :: MIT License
Requires-Python: >=3.5
Requires-Dist: numpy
